{
  "skill_name": "log-aggregation",
  "skill_dir": "skills/log-aggregation",
  "original_lines": 459,
  "hub_lines": 102,
  "reference_count": 6,
  "references": [
    {
      "filename": "elk-stack-configuration.md",
      "title": "ELK Stack Configuration",
      "line_count": 60
    },
    {
      "filename": "logstash-pipeline-configuration.md",
      "title": "Logstash Pipeline Configuration",
      "line_count": 90
    },
    {
      "filename": "filebeat-configuration.md",
      "title": "Filebeat Configuration",
      "line_count": 60
    },
    {
      "filename": "kibana-dashboard-and-alerts.md",
      "title": "Kibana Dashboard and Alerts",
      "line_count": 56
    },
    {
      "filename": "loki-configuration-kubernetes.md",
      "title": "Loki Configuration (Kubernetes)",
      "line_count": 97
    },
    {
      "filename": "log-aggregation-deployment-script.md",
      "title": "Log Aggregation Deployment Script",
      "line_count": 53
    }
  ],
  "backup": "skills/log-aggregation/SKILL.md.original",
  "domain": "infrastructure",
  "status": "restructured"
}