{
  "skill_name": "risk-assessment",
  "skill_dir": "skills/risk-assessment",
  "original_lines": 370,
  "hub_lines": 104,
  "reference_count": 4,
  "references": [
    {
      "filename": "risk-identification-techniques.md",
      "title": "Risk Identification Techniques",
      "line_count": 81
    },
    {
      "filename": "risk-analysis-matrix.md",
      "title": "Risk Analysis Matrix",
      "line_count": 94
    },
    {
      "filename": "risk-response-planning.md",
      "title": "Risk Response Planning",
      "line_count": 66
    },
    {
      "filename": "risk-monitoring-control.md",
      "title": "Risk Monitoring & Control",
      "line_count": 78
    }
  ],
  "backup": "skills/risk-assessment/SKILL.md.original",
  "domain": "process",
  "status": "restructured"
}